odoo/addons/openupgrade_framework/README.rst
odoo/addons/openupgrade_framework/__init__.py
odoo/addons/openupgrade_framework/__manifest__.py
odoo/addons/openupgrade_framework/odoo_patch/__init__.py
odoo/addons/openupgrade_framework/odoo_patch/odoo/__init__.py
odoo/addons/openupgrade_framework/odoo_patch/odoo/addons/__init__.py
odoo/addons/openupgrade_framework/odoo_patch/odoo/addons/base/__init__.py
odoo/addons/openupgrade_framework/odoo_patch/odoo/addons/base/models/__init__.py
odoo/addons/openupgrade_framework/odoo_patch/odoo/addons/base/models/ir_model.py
odoo/addons/openupgrade_framework/odoo_patch/odoo/addons/base/models/ir_module.py
odoo/addons/openupgrade_framework/odoo_patch/odoo/addons/base/models/ir_ui_view.py
odoo/addons/openupgrade_framework/odoo_patch/odoo/modules/__init__.py
odoo/addons/openupgrade_framework/odoo_patch/odoo/modules/loading.py
odoo/addons/openupgrade_framework/odoo_patch/odoo/modules/migration.py
odoo/addons/openupgrade_framework/odoo_patch/odoo/modules/module_graph.py
odoo/addons/openupgrade_framework/odoo_patch/odoo/orm/__init__.py
odoo/addons/openupgrade_framework/odoo_patch/odoo/orm/models.py
odoo/addons/openupgrade_framework/readme/CONFIGURE.md
odoo/addons/openupgrade_framework/readme/CONTRIBUTORS.md
odoo/addons/openupgrade_framework/readme/CREDITS.md
odoo/addons/openupgrade_framework/readme/DESCRIPTION.md
odoo/addons/openupgrade_framework/readme/DEVELOP.md
odoo/addons/openupgrade_framework/readme/INSTALL.md
odoo/addons/openupgrade_framework/static/description/banner.png
odoo/addons/openupgrade_framework/static/description/icon.png
odoo/addons/openupgrade_framework/static/description/index.html
odoo/addons/openupgrade_framework/tests/__init__.py
odoo/addons/openupgrade_framework/tests/test_openupgrade_framework.py
odoo_addon_openupgrade_framework-19.0.1.0.0.6.dist-info/METADATA
odoo_addon_openupgrade_framework-19.0.1.0.0.6.dist-info/WHEEL
odoo_addon_openupgrade_framework-19.0.1.0.0.6.dist-info/top_level.txt
odoo_addon_openupgrade_framework-19.0.1.0.0.6.dist-info/RECORD
