Metadata-Version: 2.1
Name: odoo-addon-openupgrade_framework
Version: 19.0.1.0.0.6
Requires-Dist: odoo==19.0.*
Requires-Dist: openupgradelib
Summary: Module to integrate in the server_wide_modules option to make upgrades between two major revisions.
Home-page: https://github.com/OCA/OpenUpgrade
License: AGPL-3
Author: Odoo Community Association (OCA), Therp BV, Opener B.V., GRAP, Hunki Enterprises BV
Author-email: support@odoo-community.org
Classifier: Programming Language :: Python
Classifier: Framework :: Odoo
Classifier: Framework :: Odoo :: 19.0
Classifier: License :: OSI Approved :: GNU Affero General Public License v3
